physical_validation/__init__.py
physical_validation/_version.py
physical_validation/ensemble.py
physical_validation/integrator.py
physical_validation/kinetic_energy.py
physical_validation/data/__init__.py
physical_validation/data/ensemble_data.py
physical_validation/data/flatfile_parser.py
physical_validation/data/gromacs_parser.py
physical_validation/data/lammps_parser.py
physical_validation/data/observable_data.py
physical_validation/data/parser.py
physical_validation/data/simulation_data.py
physical_validation/data/system_data.py
physical_validation/data/trajectory_data.py
physical_validation/data/unit_data.py
physical_validation/tests/__init__.py
physical_validation/tests/test_data_flatfile_parser.py
physical_validation/tests/test_data_gromacs_parser.py
physical_validation/tests/test_data_lammps_parser.py
physical_validation/tests/test_data_observable_data.py
physical_validation/tests/test_data_simulation_data.py
physical_validation/tests/test_data_trajectory_data.py
physical_validation/tests/test_ensemble.py
physical_validation/tests/test_ensemble_regression.py
physical_validation/tests/test_integrator.py
physical_validation/tests/test_integrator_regression.py
physical_validation/tests/test_kinetic_energy_regression.py
physical_validation/tests/test_physical_validation.py
physical_validation/tests/test_util_ensemble.py
physical_validation/tests/test_util_kinetic_energy.py
physical_validation/tests/test_util_util.py
physical_validation/tests/test_ensemble_regression/test_ensemble_regression_interval_estimate_NPT_.txt
physical_validation/tests/test_ensemble_regression/test_ensemble_regression_interval_estimate_NPT_.yml
physical_validation/tests/test_ensemble_regression/test_ensemble_regression_interval_estimate_NVT_.txt
physical_validation/tests/test_ensemble_regression/test_ensemble_regression_interval_estimate_NVT_.yml
physical_validation/tests/test_ensemble_regression/test_ensemble_regression_interval_estimate_muVT_.txt
physical_validation-1.0.5.dist-info/LICENSE
physical_validation-1.0.5.dist-info/METADATA
physical_validation-1.0.5.dist-info/WHEEL
physical_validation-1.0.5.dist-info/top_level.txt
physical_validation-1.0.5.dist-info/RECORD
