Metadata-Version: 2.1
Name: physical-validation
Version: 1.0.5
Summary: UNKNOWN
Home-page: https://physical-validation.readthedocs.io
Author: Pascal T. Merz and Michael R. Shirts
Author-email: pascal.merz@me.com, michael.shirts@colorado.edu
License: MIT
Project-URL: Bug Reports, https://github.com/shirtsgroup/physical_validation/issues
Project-URL: Documentation, https://physical-validation.readthedocs.io
Project-URL: Source, https://github.com/shirtsgroup/physical_validation
Keywords: physical-validation,molecular-simulation,molecular-dynamics,molecular-mechanics
Platform: UNKNOWN
Classifier: Development Status :: 5 - Production/Stable
Classifier: Intended Audience :: Science/Research
Classifier: License :: OSI Approved :: MIT License
Classifier: Natural Language :: English
Classifier: Programming Language :: Python :: 3
Classifier: Programming Language :: Python :: 3.7
Classifier: Programming Language :: Python :: 3.8
Classifier: Programming Language :: Python :: 3.9
Classifier: Programming Language :: Python :: 3.10
Classifier: Programming Language :: Python :: 3.11
Classifier: Environment :: Console
Classifier: Topic :: Scientific/Engineering
Classifier: Topic :: Scientific/Engineering :: Bio-Informatics
Classifier: Topic :: Scientific/Engineering :: Chemistry
Classifier: Topic :: Software Development :: Libraries :: Python Modules
License-File: LICENSE
Requires-Dist: numpy
Requires-Dist: scipy
Requires-Dist: pymbar
Requires-Dist: matplotlib
